{"header": { "version" : "1.0"},"plrs" : [{"plrNum" : "05379","plrName" : "Bob Lowry","currentYear" : "2012", "tours" : [{"tourCodeLC" : "s","tourCodeUC" : "S","tourDesc" : "Champions Tour", "trnDetails" : [{"endDate" : "6\/29\/86", "trn" : {"trnNum" : "018","permNum" : "512","officialFlg" : "Y", "trnName" : "U.S. Senior Open"}, "finPos" : {"finCode" : "T","playOffFlg" : "", "value" : "T42"}, "" : "", "" : "", "" : "", "offMoney" : "", "ssFinPosFinCode" : "0", "ssFinPos" : "999", "ssMoney" : "", "scr" : {"rounds" : [{"rndNum" : "Round 1","rndScr" : "75","posInField" : "T48"},{"rndNum" : "Round 2","rndScr" : "77","posInField" : "T50"},{"rndNum" : "Round 3","rndScr" : "73","posInField" : "T41"},{"rndNum" : "Round 4","rndScr" : "76","posInField" : "T42"}], "totalScr" : "301", "relToPar" : "+13"}}],"totals" : {"evnts" : "1","rnds" : "4","first" : "","seconds" : "","thirds" : "","top10" : "","top25" : "","cutsMade" : "1","cutsMissed" : "","wd" : "","dq" : "","offMoney" : "","moneyRank" : "", "points" : [{"pointName" : "","pointRank" : "","pointValue" : "", "pointId" : "000"}]},"bests" : {"bestRnds" : [{"bstRndScr" : "073","trnName" : "U.S. Senior Open","trnNum" : "018","permNum" : "512","rndNum" : "03"}], "bestFinVics" : [{"finPos" : "042","finCode" : "T","playOffFlg" : "","trn" : "U.S. Senior Open","trnNum" : "018","permNum" : "512","officialFlg" : ""}]}}]}]}