{"header": { "version" : "1.0"},"plrs" : [{"plrNum" : "01177","plrName" : "Billy Casper","years" : [{"year" : "1996","disclaimer" : "Player did not meet the minimum number of rounds requirement to be officially ranked. The rank indicated is the position the player would be ranked if the minimum had been met.","tours" : [{"tourCodeLC" : "r","tourCodeUC" : "R","tourName" : "PGA TOUR","minRndsMet" : "N","year" : "1996","lastTrnProc" : "End of Year","trnNum" : "999","permNum" : "999","statCats" : [{"catName" : "Recap","stats" : [{"statID" : "101","name" : "Driving Distance","value" : "242.8","rank" : "999","projRank" : "190","additionals" : [{"title" : "Total Distance","value" : "1,942"},{"title" : "Total Drives","value" : "8"}]},{"statID" : "102","name" : "Driving Accuracy Percentage","value" : "82.14%","rank" : "999","projRank" : "1","additionals" : [{"title" : "Fairways Hit","value" : "46"},{"title" : "Possible Fairways","value" : "56"}]},{"statID" : "103","name" : "Greens in Regulation Percentage","value" : "41.67%","rank" : "999","projRank" : "191","additionals" : [{"title" : "Greens Hit","value" : "30"},{"title" : "# Holes","value" : "72"}]},{"statID" : "156","name" : "Birdie Average","value" : "2.00","rank" : "999","projRank" : "191","additionals" : [{"title" : "# of Birdies","value" : "8"},{"title" : "Total Rounds","value" : "4"}]},{"statID" : "120","name" : "Scoring Average","value" : "76.726","rank" : "999","projRank" : "191","additionals" : [{"title" : "Total Strokes","value" : "311"},{"title" : "Total Adjustment","value" : "- 4.096"}]},{"statID" : "111","name" : "Sand Save Percentage","value" : "50.00%","rank" : "999","projRank" : "132","additionals" : [{"title" : "# Saves","value" : "4"},{"title" : "# Bunkers","value" : "8"}]},{"statID" : "129","name" : "Total Driving","value" : "","rank" : "999","projRank" : "","additionals" : [{"title" : "Distance Rank","value" : "999"},{"title" : "Accuracy Rank","value" : "999"}]},{"statID" : "158","name" : "Ball Striking","value" : "","rank" : "999","projRank" : "","additionals" : [{"title" : "Total Drv Rank","value" : "999"},{"title" : "GIR Rank","value" : "999"}]}]},{"catName" : "Off the Tee","stats" : [{"statID" : "101","name" : "Driving Distance","value" : "242.8","rank" : "999","projRank" : "190","additionals" : [{"title" : "Total Distance","value" : "1,942"},{"title" : "Total Drives","value" : "8"}]},{"statID" : "102","name" : "Driving Accuracy Percentage","value" : "82.14%","rank" : "999","projRank" : "1","additionals" : [{"title" : "Fairways Hit","value" : "46"},{"title" : "Possible Fairways","value" : "56"}]},{"statID" : "129","name" : "Total Driving","value" : "","rank" : "999","projRank" : "","additionals" : [{"title" : "Distance Rank","value" : "999"},{"title" : "Accuracy Rank","value" : "999"}]}]},{"catName" : "Approach the Green","stats" : [{"statID" : "103","name" : "Greens in Regulation Percentage","value" : "41.67%","rank" : "999","projRank" : "191","additionals" : [{"title" : "Greens Hit","value" : "30"},{"title" : "# Holes","value" : "72"}]}]},{"catName" : "Around the Green","stats" : [{"statID" : "111","name" : "Sand Save Percentage","value" : "50.00%","rank" : "999","projRank" : "132","additionals" : [{"title" : "# Saves","value" : "4"},{"title" : "# Bunkers","value" : "8"}]},{"statID" : "130","name" : "Scrambling","value" : "30.00%","rank" : "999","projRank" : "191","additionals" : [{"title" : "Par or Better","value" : "6"},{"title" : "Missed GIR","value" : "20"}]}]},{"catName" : "Putting","stats" : [{"statID" : "104","name" : "Putting Average","value" : "1.933","rank" : "999","projRank" : "191","additionals" : [{"title" : "GIR Putts","value" : "58"},{"title" : "Greens Hit","value" : "30"}]},{"statID" : "402","name" : "Overall Putting Average","value" : ".875","rank" : "999","projRank" : "1","additionals" : [{"title" : "# of Putts","value" : "63"},{"title" : "# of Holes","value" : "72"}]},{"statID" : "413","name" : "One-Putt Percentage","value" : "13.89%","rank" : "999","projRank" : "191","additionals" : [{"title" : "# of 1 putts","value" : "10"},{"title" : "# of holes","value" : "72"}]},{"statID" : "426","name" : "3-Putt Avoidance","value" : "4.17%","rank" : "999","projRank" : "180","additionals" : [{"title" : "Total 3 Putts","value" : "3"},{"title" : "Total Holes (overall)","value" : "72"}]},{"statID" : "119","name" : "Putts Per Round","value" : "29.00","rank" : "999","projRank" : "37","additionals" : [{"title" : "Total Putts","value" : "116"},{"title" : "Total Rounds","value" : "4"}]},{"statID" : "393","name" : "Putts per Round - Round 1","value" : "29.00","rank" : "999","projRank" : "37","additionals" : [{"title" : "Total Putts","value" : "29"},{"title" : "Total Rounds","value" : "1"}]},{"statID" : "394","name" : "Putts per Round - Round 2","value" : "34.00","rank" : "999","projRank" : "191","additionals" : [{"title" : "Total Putts","value" : "34"},{"title" : "Total Rounds","value" : "1"}]},{"statID" : "115","name" : "Birdie or Better Conversion Percentage","value" : "2.67%","rank" : "999","projRank" : "148","additionals" : [{"title" : "# Birdies","value" : "8"},{"title" : "Greens Hit","value" : "30"}]}]},{"catName" : "Scoring","stats" : [{"statID" : "299","name" : "Lowest Round","value" : "75","rank" : "585","projRank" : "","additionals" : [{"title" : "Tourn\/Course","value" : "Masters\/Augusta"},{"title" : "Round","value" : "1"}]},{"statID" : "120","name" : "Scoring Average","value" : "76.726","rank" : "999","projRank" : "191","additionals" : [{"title" : "Total Strokes","value" : "311"},{"title" : "Total Adjustment","value" : "- 4.096"}]},{"statID" : "108","name" : "Scoring Average (Actual)","value" : "77.75","rank" : "999","projRank" : "191","additionals" : [{"title" : "Total Strokes","value" : "311"},{"title" : "Total Rounds","value" : "4"}]},{"statID" : "156","name" : "Birdie Average","value" : "2.00","rank" : "999","projRank" : "191","additionals" : [{"title" : "# of Birdies","value" : "8"},{"title" : "Total Rounds","value" : "4"}]},{"statID" : "107","name" : "Total Birdies","value" : "8","rank" : "999","projRank" : "191","additionals" : [{"title" : "","value" : ""},{"title" : "","value" : ""}]},{"statID" : "106","name" : "Total Eagles","value" : "0","rank" : "999","projRank" : "190","additionals" : [{"title" : "","value" : ""},{"title" : "","value" : ""}]},{"statID" : "105","name" : "Par Breakers","value" : "11.11%","rank" : "999","projRank" : "191","additionals" : [{"title" : "# Birdies\/Eagles","value" : "8"},{"title" : "# Holes","value" : "72"}]},{"statID" : "148","name" : "Round 1 Scoring Average","value" : "75.00","rank" : "999","projRank" : "191","additionals" : [{"title" : "Total Strokes","value" : "150"},{"title" : "Total Rounds","value" : "2"}]},{"statID" : "149","name" : "Round 2 Scoring Average","value" : "80.50","rank" : "999","projRank" : "191","additionals" : [{"title" : "Total Strokes","value" : "161"},{"title" : "Total Rounds","value" : "2"}]},{"statID" : "207","name" : "Front 9 Scoring Average","value" : "38.00","rank" : "999","projRank" : "191","additionals" : [{"title" : "Total Strokes","value" : "152"},{"title" : "Total Holes","value" : "4"}]},{"statID" : "208","name" : "Back 9 Scoring Average","value" : "39.75","rank" : "999","projRank" : "190","additionals" : [{"title" : "Total Strokes","value" : "159"},{"title" : "Total Holes","value" : "4"}]},{"statID" : "142","name" : "Par 3 Scoring Average","value" : "3.56","rank" : "999","projRank" : "191","additionals" : [{"title" : "Total Strokes","value" : "57"},{"title" : "Total Holes","value" : "16"}]},{"statID" : "143","name" : "Par 4 Scoring Average","value" : "4.35","rank" : "999","projRank" : "190","additionals" : [{"title" : "Total Strokes","value" : "174"},{"title" : "Total Holes","value" : "40"}]},{"statID" : "144","name" : "Par 5 Scoring Average","value" : "5.00","rank" : "999","projRank" : "191","additionals" : [{"title" : "Total Strokes","value" : "80"},{"title" : "Total Holes","value" : "16"}]},{"statID" : "112","name" : "Par 3 Birdie or Better Leaders","value" : ".00%","rank" : "999","projRank" : "191","additionals" : [{"title" : "Par 3 Birdies or Better","value" : "0"},{"title" : "Par 3 Holes","value" : "16"}]},{"statID" : "113","name" : "Par 4 Birdie or Better Leaders","value" : "10.00%","rank" : "999","projRank" : "190","additionals" : [{"title" : "Par 4 Birdies or Better","value" : "4"},{"title" : "Par 4 Holes","value" : "40"}]},{"statID" : "114","name" : "Par 5 Birdie or Better Leaders","value" : "25.00%","rank" : "999","projRank" : "191","additionals" : [{"title" : "Par 5 Birdies or Better","value" : "4"},{"title" : "Par 5 Holes","value" : "16"}]},{"statID" : "352","name" : "Birdie or Better Percentage","value" : "11.11%","rank" : "999","projRank" : "191","additionals" : [{"title" : "Total Birdies","value" : "8"},{"title" : "Total Holes","value" : "72"}]},{"statID" : "160","name" : "Bounce Back","value" : "21.74%","rank" : "999","projRank" : "33","additionals" : [{"title" : "","value" : ""},{"title" : "","value" : ""}]}]},{"catName" : "Streaks","stats" : [{"statID" : "295","name" : "Best YTD 1-Putt or Better Streak","value" : "2","rank" : "495","projRank" : "","additionals" : [{"title" : "","value" : ""},{"title" : "","value" : ""}]},{"statID" : "294","name" : "Best YTD Streak w\/o a 3-Putt","value" : "17","rank" : "509","projRank" : "","additionals" : [{"title" : "Current Streak","value" : "2"},{"title" : "","value" : ""}]},{"statID" : "483","name" : "Current Streak without a 3-Putt","value" : "2","rank" : "999","projRank" : "169","additionals" : [{"title" : "","value" : ""},{"title" : "","value" : ""}]},{"statID" : "297","name" : "Consecutive Fairways Hit","value" : "12","rank" : "223","projRank" : "","additionals" : [{"title" : "Current Streak","value" : "12"},{"title" : "","value" : ""}]},{"statID" : "298","name" : "Consecutive GIR","value" : "2","rank" : "550","projRank" : "","additionals" : [{"title" : "Current Streak","value" : "0"},{"title" : "Round","value" : "2"}]},{"statID" : "452","name" : "Consecutive Holes Below Par","value" : "2","rank" : "303","projRank" : "","additionals" : [{"title" : "","value" : ""},{"title" : "","value" : ""}]},{"statID" : "02672","name" : "Consecutive Birdies Streak","value" : "2","rank" : "279","projRank" : "","additionals" : [{"title" : "","value" : ""},{"title" : "","value" : ""}]}]}]},{"tourCodeLC" : "s","tourCodeUC" : "S","tourName" : "Champions Tour","minRndsMet" : "N","year" : "1996","lastTrnProc" : "End of Year","trnNum" : "999","permNum" : "999","statCats" : [{"catName" : "Recap","stats" : [{"statID" : "101","name" : "Driving Distance","value" : "244.2","rank" : "999","projRank" : "","additionals" : [{"title" : "Total Distance","value" : "14,654"},{"title" : "Total Drives","value" : "60"}]},{"statID" : "102","name" : "Driving Accuracy Percentage","value" : "65.79%","rank" : "999","projRank" : "","additionals" : [{"title" : "Fairways Hit","value" : "275"},{"title" : "Possible Fairways","value" : "418"}]},{"statID" : "103","name" : "Greens in Regulation Percentage","value" : "52.96%","rank" : "999","projRank" : "","additionals" : [{"title" : "Greens Hit","value" : "286"},{"title" : "# Holes","value" : "540"}]},{"statID" : "104","name" : "Putting Average","value" : "1.923","rank" : "999","projRank" : "","additionals" : [{"title" : "GIR Putts","value" : "550"},{"title" : "Greens Hit","value" : "286"}]},{"statID" : "155","name" : "Eagles (Holes per)","value" : "540.0","rank" : "999","projRank" : "","additionals" : [{"title" : "# of Holes","value" : "540"},{"title" : "# of Eagles","value" : "1"}]},{"statID" : "156","name" : "Birdie Average","value" : "1.67","rank" : "999","projRank" : "","additionals" : [{"title" : "# of Birdies","value" : "50"},{"title" : "","value" : ""}]},{"statID" : "108","name" : "Scoring Average (Actual)","value" : "75.83","rank" : "999","projRank" : "","additionals" : [{"title" : "Total Strokes","value" : "2,275"},{"title" : "Total Rounds","value" : "30"}]},{"statID" : "111","name" : "Sand Save Percentage","value" : "44.93%","rank" : "999","projRank" : "","additionals" : [{"title" : "# Saves","value" : "31"},{"title" : "# Bunkers","value" : "69"}]},{"statID" : "129","name" : "Total Driving","value" : "","rank" : "999","projRank" : "","additionals" : [{"title" : "Distance Rank","value" : "999"},{"title" : "Accuracy Rank","value" : "999"}]},{"statID" : "127","name" : "All-Around Ranking","value" : "","rank" : "999","projRank" : "","additionals" : [{"title" : "","value" : ""},{"title" : "","value" : ""}]},{"statID" : "109","name" : "Money Leaders","value" : "$14,604","rank" : "110","projRank" : "","additionals" : [{"title" : "","value" : ""},{"title" : "YTD Victories","value" : ""}]},{"statID" : "158","name" : "Ball Striking","value" : "","rank" : "999","projRank" : "","additionals" : [{"title" : "Total Drv Rank","value" : "999"},{"title" : "GIR Rank","value" : "999"}]}]},{"catName" : "Off the Tee","stats" : [{"statID" : "101","name" : "Driving Distance","value" : "244.2","rank" : "999","projRank" : "","additionals" : [{"title" : "Total Distance","value" : "14,654"},{"title" : "Total Drives","value" : "60"}]},{"statID" : "102","name" : "Driving Accuracy Percentage","value" : "65.79%","rank" : "999","projRank" : "","additionals" : [{"title" : "Fairways Hit","value" : "275"},{"title" : "Possible Fairways","value" : "418"}]},{"statID" : "129","name" : "Total Driving","value" : "","rank" : "999","projRank" : "","additionals" : [{"title" : "Distance Rank","value" : "999"},{"title" : "Accuracy Rank","value" : "999"}]}]},{"catName" : "Approach the Green","stats" : [{"statID" : "103","name" : "Greens in Regulation Percentage","value" : "52.96%","rank" : "999","projRank" : "","additionals" : [{"title" : "Greens Hit","value" : "286"},{"title" : "# Holes","value" : "540"}]}]},{"catName" : "Around the Green","stats" : [{"statID" : "111","name" : "Sand Save Percentage","value" : "44.93%","rank" : "999","projRank" : "","additionals" : [{"title" : "# Saves","value" : "31"},{"title" : "# Bunkers","value" : "69"}]},{"statID" : "130","name" : "Scrambling","value" : "51.97%","rank" : "999","projRank" : "","additionals" : [{"title" : "Par or Better","value" : "132"},{"title" : "Missed GIR","value" : "254"}]}]},{"catName" : "Putting","stats" : [{"statID" : "104","name" : "Putting Average","value" : "1.923","rank" : "999","projRank" : "","additionals" : [{"title" : "GIR Putts","value" : "550"},{"title" : "Greens Hit","value" : "286"}]},{"statID" : "402","name" : "Overall Putting Average","value" : "1.669","rank" : "999","projRank" : "","additionals" : [{"title" : "# of Putts","value" : "901"},{"title" : "# of Holes","value" : "540"}]},{"statID" : "413","name" : "One Putt Percentage","value" : "35.56%","rank" : "999","projRank" : "","additionals" : [{"title" : "# of 1 putts","value" : "192"},{"title" : "# of holes","value" : "540"}]},{"statID" : "426","name" : "3 Putt Avoidance","value" : "5.37%","rank" : "999","projRank" : "","additionals" : [{"title" : "Total 3 Putts","value" : "29"},{"title" : "Total Holes (overall)","value" : "540"}]},{"statID" : "119","name" : "Putts Per Round","value" : "30.03","rank" : "999","projRank" : "","additionals" : [{"title" : "Total Putts","value" : "901"},{"title" : "Total Rounds","value" : "30"}]},{"statID" : "393","name" : "Putts per Round - Round 1","value" : "29.80%","rank" : "999","projRank" : "","additionals" : [{"title" : "Total Putts","value" : "298"},{"title" : "Total Rounds","value" : "10"}]},{"statID" : "394","name" : "Putts per Round - Round 2","value" : "30.90%","rank" : "999","projRank" : "","additionals" : [{"title" : "Total Putts","value" : "309"},{"title" : "Total Rounds","value" : "10"}]},{"statID" : "395","name" : "Putts per Round - Round 3","value" : "29.33%","rank" : "999","projRank" : "","additionals" : [{"title" : "Total Putts","value" : "264"},{"title" : "Total Rounds","value" : "9"}]},{"statID" : "396","name" : "Putts per Round - Round 4","value" : "30.00%","rank" : "999","projRank" : "","additionals" : [{"title" : "Total Putts","value" : "30"},{"title" : "Total Rounds","value" : "1"}]},{"statID" : "115","name" : "Birdie or Better Conversion Percentage","value" : "1.75%","rank" : "999","projRank" : "","additionals" : [{"title" : "# Birdies","value" : "50"},{"title" : "Greens Hit","value" : "286"}]}]},{"catName" : "Scoring","stats" : [{"statID" : "299","name" : "Lowest Round","value" : "70","rank" : "129","projRank" : "","additionals" : [{"title" : "Tourn\/Course","value" : "Cadillac NFL\/UP"},{"title" : "Round","value" : "3"}]},{"statID" : "108","name" : "Scoring Average (Actual)","value" : "75.83","rank" : "999","projRank" : "","additionals" : [{"title" : "Total Strokes","value" : "2,275"},{"title" : "Total Rounds","value" : "30"}]},{"statID" : "156","name" : "Birdie Average","value" : "1.67","rank" : "999","projRank" : "","additionals" : [{"title" : "# of Birdies","value" : "50"},{"title" : "","value" : ""}]},{"statID" : "106","name" : "Total Eagles","value" : "1","rank" : "999","projRank" : "","additionals" : [{"title" : "","value" : ""},{"title" : "","value" : ""}]},{"statID" : "107","name" : "Total Birdies","value" : "50","rank" : "999","projRank" : "","additionals" : [{"title" : "","value" : ""},{"title" : "","value" : ""}]},{"statID" : "105","name" : "Par Breakers","value" : "9.44%","rank" : "999","projRank" : "","additionals" : [{"title" : "# Birdies\/Eagles","value" : "51"},{"title" : "# Holes","value" : "540"}]},{"statID" : "148","name" : "Round 1 Scoring Average","value" : "74.80","rank" : "999","projRank" : "","additionals" : [{"title" : "Total Strokes","value" : "748"},{"title" : "Total Rounds","value" : "10"}]},{"statID" : "149","name" : "Round 2 Scoring Average","value" : "76.90","rank" : "999","projRank" : "","additionals" : [{"title" : "Total Strokes","value" : "769"},{"title" : "Total Rounds","value" : "10"}]},{"statID" : "117","name" : "Round 3 Scoring Average","value" : "75.56","rank" : "999","projRank" : "","additionals" : [{"title" : "Total Strokes","value" : "680"},{"title" : "Total Rounds","value" : "9"}]},{"statID" : "118","name" : "Scoring Average Final Rnd","value" : "75.89","rank" : "999","projRank" : "","additionals" : [{"title" : "Total Strokes","value" : "683"},{"title" : "Total Rounds","value" : "9"}]},{"statID" : "155","name" : "Eagles (Holes per)","value" : "540.0","rank" : "999","projRank" : "","additionals" : [{"title" : "# of Holes","value" : "540"},{"title" : "# of Eagles","value" : "1"}]},{"statID" : "142","name" : "Par 3 Scoring Average","value" : "3.36","rank" : "999","projRank" : "","additionals" : [{"title" : "Total Strokes","value" : "410"},{"title" : "Total Holes","value" : "122"}]},{"statID" : "143","name" : "Par 4 Scoring Average","value" : "4.29","rank" : "999","projRank" : "","additionals" : [{"title" : "Total Strokes","value" : "1,307"},{"title" : "Total Holes","value" : "305"}]},{"statID" : "144","name" : "Par 5 Scoring Average","value" : "4.94","rank" : "999","projRank" : "","additionals" : [{"title" : "Total Strokes","value" : "558"},{"title" : "Total Holes","value" : "113"}]},{"statID" : "219","name" : "Final Round Performance","value" : "77.78%","rank" : "999","projRank" : "","additionals" : [{"title" : "","value" : ""},{"title" : "","value" : ""}]},{"statID" : "112","name" : "Par 3 Birdie or Better Leaders","value" : "3.28%","rank" : "999","projRank" : "","additionals" : [{"title" : "Par 3 Birdies or Better","value" : "4"},{"title" : "Par 3 Holes","value" : "122"}]},{"statID" : "113","name" : "Par 4 Birdie or Better Leaders","value" : "8.52%","rank" : "999","projRank" : "","additionals" : [{"title" : "Par 4 Birdies or Better","value" : "26"},{"title" : "Par 4 Holes","value" : "305"}]},{"statID" : "114","name" : "Par 5 Birdie or Better Leaders","value" : "18.58%","rank" : "999","projRank" : "","additionals" : [{"title" : "Par 5 Birdies or Better","value" : "21"},{"title" : "Par 5 Holes","value" : "113"}]},{"statID" : "352","name" : "Birdie or Better Percentage","value" : "9.44%","rank" : "999","projRank" : "","additionals" : [{"title" : "Total Birdies","value" : "51"},{"title" : "Total Holes","value" : "540"}]},{"statID" : "160","name" : "Bounce Back","value" : "9.42%","rank" : "999","projRank" : "","additionals" : [{"title" : "","value" : ""},{"title" : "","value" : ""}]}]},{"catName" : "Streaks","stats" : [{"statID" : "482","name" : "YTD Par or Better Streak","value" : "2","rank" : "98","projRank" : "","additionals" : [{"title" : "","value" : ""},{"title" : "","value" : ""}]},{"statID" : "295","name" : "Best YTD 1-Putt or Better Streak","value" : "6","rank" : "70","projRank" : "","additionals" : [{"title" : "","value" : ""},{"title" : "","value" : ""}]},{"statID" : "294","name" : "Best YTD Streak w\/o a 3-Putt","value" : "75","rank" : "103","projRank" : "","additionals" : [{"title" : "Current Streak","value" : "0"},{"title" : "","value" : ""}]},{"statID" : "296","name" : "Consecutive Sand Saves","value" : "6","rank" : "33","projRank" : "","additionals" : [{"title" : "Current Streak","value" : "3"},{"title" : "Round","value" : "3"}]},{"statID" : "297","name" : "Consecutive Fairways Hit","value" : "14","rank" : "87","projRank" : "","additionals" : [{"title" : "Current Streak","value" : "1"},{"title" : "","value" : ""}]},{"statID" : "298","name" : "Consecutive GIR","value" : "9","rank" : "115","projRank" : "","additionals" : [{"title" : "Current Streak","value" : "1"},{"title" : "Round","value" : "1"}]},{"statID" : "452","name" : "Consecutive Holes below Par","value" : "2","rank" : "117","projRank" : "","additionals" : [{"title" : "","value" : ""},{"title" : "","value" : ""}]},{"statID" : "449","name" : "Consecutive Par 3 Birdies","value" : "1","rank" : "121","projRank" : "","additionals" : [{"title" : "","value" : ""},{"title" : "","value" : ""}]},{"statID" : "450","name" : "Consecutive Par 4 Birdies","value" : "1","rank" : "158","projRank" : "","additionals" : [{"title" : "","value" : ""},{"title" : "","value" : ""}]},{"statID" : "451","name" : "Consecutive Par 5 Birdies","value" : "2","rank" : "122","projRank" : "","additionals" : [{"title" : "","value" : ""},{"title" : "","value" : ""}]},{"statID" : "02672","name" : "Consecutive Birdies Streak","value" : "2","rank" : "110","projRank" : "","additionals" : [{"title" : "","value" : ""},{"title" : "","value" : ""}]},{"statID" : "02673","name" : "Consecutive Birdies\/Eagles streak","value" : "1","rank" : "72","projRank" : "","additionals" : [{"title" : "","value" : ""},{"title" : "","value" : ""}]}]}]}]}]}]}