{"header": { "version" : "1.0"},"plrs" : [{"plrNum" : "06595","plrName" : "Kevin Sutherland","currentYear" : "2016", "tours" : [{"tourCodeLC" : "s","tourCodeUC" : "S","tourDesc" : "PGA TOUR Champions","year" : "2016", "trnDetails" : [{"endDate" : "2\/07\/16", "trn" : {"trnNum" : "020","permNum" : "009","officialFlg" : "Y", "trnName" : "Allianz Championship"}, "finPos" : {"finCode" : "T","playOffFlg" : "", "value" : "T10"}, "" : "", "" : "", "" : "", "offMoney" : "$38,850.00", "ssFinPosFinCode" : "", "ssFinPos" : "999", "moneyRank": "26","ssMoney" : "", "scr" : {"rounds" : [{"rndNum" : "Round 1","rndScr" : "70","posInField" : "T13"},{"rndNum" : "Round 2","rndScr" : "68","posInField" : "T10"},{"rndNum" : "Round 3","rndScr" : "71","posInField" : "T10"}], "totalScr" : "209", "relToPar" : "-7"}},{"endDate" : "2\/14\/16", "trn" : {"trnNum" : "030","permNum" : "552","officialFlg" : "Y", "trnName" : "Chubb Classic"}, "finPos" : {"finCode" : "T","playOffFlg" : "", "value" : "T11"}, "" : "", "" : "", "" : "", "offMoney" : "$34,000.00", "ssFinPosFinCode" : "", "ssFinPos" : "999", "moneyRank": "21","ssMoney" : "", "scr" : {"rounds" : [{"rndNum" : "Round 1","rndScr" : "68","posInField" : "T4"},{"rndNum" : "Round 2","rndScr" : "71","posInField" : "T13"},{"rndNum" : "Round 3","rndScr" : "69","posInField" : "T11"}], "totalScr" : "208", "relToPar" : "-8"}},{"endDate" : "3\/20\/16", "trn" : {"trnNum" : "040","permNum" : "018","officialFlg" : "Y", "trnName" : "Tucson Conquistadores Classic"}, "finPos" : {"finCode" : "T","playOffFlg" : "", "value" : "T11"}, "" : "", "" : "", "" : "", "offMoney" : "$34,000.00", "ssFinPosFinCode" : "", "ssFinPos" : "999", "moneyRank": "22","ssMoney" : "", "scr" : {"rounds" : [{"rndNum" : "Round 1","rndScr" : "70","posInField" : "T24"},{"rndNum" : "Round 2","rndScr" : "68","posInField" : "T17"},{"rndNum" : "Round 3","rndScr" : "69","posInField" : "T11"}], "totalScr" : "207", "relToPar" : "-9"}},{"endDate" : "4\/03\/16", "trn" : {"trnNum" : "050","permNum" : "011","officialFlg" : "Y", "trnName" : "Mississippi Gulf Resort Classic presented by C Spire"}, "finPos" : {"finCode" : "T","playOffFlg" : "", "value" : "T37"}, "" : "", "" : "", "" : "", "offMoney" : "$8,640.00", "ssFinPosFinCode" : "", "ssFinPos" : "999", "moneyRank": "25","ssMoney" : "", "scr" : {"rounds" : [{"rndNum" : "Round 1","rndScr" : "75","posInField" : "T43"},{"rndNum" : "Round 2","rndScr" : "74","posInField" : "T48"},{"rndNum" : "Round 3","rndScr" : "71","posInField" : "T37"}], "totalScr" : "220", "relToPar" : "+4"}},{"endDate" : "4\/17\/16", "trn" : {"trnNum" : "060","permNum" : "015","officialFlg" : "Y", "trnName" : "Mitsubishi Electric Classic"}, "finPos" : {"finCode" : "T","playOffFlg" : "", "value" : "T9"}, "" : "", "" : "", "" : "", "offMoney" : "$48,600.00", "ssFinPosFinCode" : "", "ssFinPos" : "999", "moneyRank": "19","ssMoney" : "", "scr" : {"rounds" : [{"rndNum" : "Round 1","rndScr" : "72","posInField" : "T23"},{"rndNum" : "Round 2","rndScr" : "70","posInField" : "T19"},{"rndNum" : "Round 3","rndScr" : "67","posInField" : "T9"}], "totalScr" : "209", "relToPar" : "-7"}},{"endDate" : "4\/24\/16", "trn" : {"trnNum" : "070","permNum" : "504","officialFlg" : "Y", "trnName" : "Bass Pro Shops Legends of Golf at Big Cedar Lodge"}, "finPos" : {"finCode" : "T","playOffFlg" : "", "value" : "T8"}, "" : "", "" : "", "" : "", "offMoney" : "$38,750.00", "ssFinPosFinCode" : "", "ssFinPos" : "999", "moneyRank": "21","ssMoney" : "", "scr" : {"rounds" : [{"rndNum" : "Round 1","rndScr" : "63","posInField" : "T3"},{"rndNum" : "Round 2","rndScr" : "50","posInField" : "T13"},{"rndNum" : "Round 3","rndScr" : "49","posInField" : "T8"}], "totalScr" : "162", "relToPar" : "-17"}}],"totals" : {"evnts" : "6","rnds" : "15","first" : "","seconds" : "","thirds" : "","top10" : "3","top25" : "5","cutsMade" : "6","cutsMissed" : "","wd" : "","dq" : "","offMoney" : "$202,840","moneyRank" : "21","finalsMoney" : "","finalsRank" : "","priorityRank" : "", "points" : [{"pointName" : "SCHWAB CUP","pointRank" : "","pointValue" : "", "pointId" : "193"}]},"bests" : {"bestRnds" : [{"bstRndScr" : "067","trnName" : "Mitsubishi Electric Classic","trnNum" : "060","permNum" : "015","rndNum" : "03"}], "bestFinVics" : [{"finPos" : "008","finCode" : "T","playOffFlg" : "","trn" : "Bass Pro Shops Legends of Golf at Big Cedar Lodge","trnNum" : "070","permNum" : "504","officialFlg" : ""}]}}]}]}